{
    "label": "Minna Nihongo Book 1 Lesson 8",
    "vocab": [
        {
            "kanji": null,
            "kana": "ハンサム",
            "en": "handsome"
        },
        {
            "kanji": null,
            "kana": "きれい",
            "en": "beautiful, clean"
        },
        {
            "kanji": "静か",
            "kana": "しずか",
            "en": "quiet"
        },
        {
            "kanji": null,
            "kana": "にぎやか",
            "en": "lively"
        },
        {
            "kanji": "有名",
            "kana": "ゆうめい",
            "en": "famous"
        },
        {
            "kanji": "親切",
            "kana": "しんせつ",
            "en": "kind"
        },
        {
            "kanji": "元気",
            "kana": "げんき",
            "en": "healthy, sound, cheerful"
        },
        {
            "kanji": "暇",
            "kana": "ひま",
            "en": "free (time)"
        },
        {
            "kanji": "便利",
            "kana": "べんり",
            "en": "convenient"
        },
        {
            "kanji": null,
            "kana": "すてき",
            "en": "fine, nice, wonderful"
        },
        {
            "kanji": "大きい",
            "kana": "おおきい",
            "en": "big, large"
        },
        {
            "kanji": "小さい",
            "kana": "ちいさい",
            "en": "small, little"
        },
        {
            "kanji": "新しい",
            "kana": "あたらしい",
            "en": "new"
        },
        {
            "kanji": "古い",
            "kana": "ふるい",
            "en": "old (not of age)"
        },
        {
            "kanji": null,
            "kana": "いい",
            "en": "good"
        },
        {
            "kanji": "悪い",
            "kana": "わるい",
            "en": "bad"
        },
        {
            "kanji": "暑い",
            "kana": "あつい",
            "en": "hot (weather)"
        },
        {
            "kanji": "熱い",
            "kana": "あつい",
            "en": "hot (touch)"
        },
        {
            "kanji": "寒い",
            "kana": "さむい",
            "en": "cold (weather)"
        },
        {
            "kanji": "冷たい",
            "kana": "つめたい",
            "en": "cold (touch)"
        },
        {
            "kanji": "難しい",
            "kana": "むずかしい",
            "en": "difficult"
        },
        {
            "kanji": "易しい",
            "kana": "やさしい",
            "en": "easy"
        },
        {
            "kanji": "高い",
            "kana": "たかい",
            "en": "expensive, tall, high"
        },
        {
            "kanji": "安い",
            "kana": "やすい",
            "en": "inexpensive"
        },
        {
            "kanji": "低い",
            "kana": "ひくい",
            "en": "low"
        },
        {
            "kanji": null,
            "kana": "おもしろい",
            "en": "interesting"
        },
        {
            "kanji": null,
            "kana": "おいしい",
            "en": "delicious, tasty"
        },
        {
            "kanji": "忙しい",
            "kana": "いそがしい",
            "en": "busy"
        },
        {
            "kanji": "楽しい",
            "kana": "たのしい",
            "en": "enjoyable"
        },
        {
            "kanji": "白い",
            "kana": "しろい",
            "en": "white"
        },
        {
            "kanji": "黒い",
            "kana": "くろい",
            "en": "black"
        },
        {
            "kanji": "赤い",
            "kana": "あかい",
            "en": "red"
        },
        {
            "kanji": "青い",
            "kana": "あおい",
            "en": "blue"
        },
        {
            "kanji": "桜",
            "kana": "さくら",
            "en": "cherry (blossom)"
        },
        {
            "kanji": null,
            "kana": "やま",
            "en": "mountain"
        },
        {
            "kanji": "町",
            "kana": "まち",
            "en": "town, city"
        },
        {
            "kanji": "食べ物",
            "kana": "たべもの",
            "en": "food"
        },
        {
            "kanji": "車",
            "kana": "くるま",
            "en": "car, vehicle"
        },
        {
            "kanji": "甘い",
            "kana": "あまい",
            "en": "sweet"
        },
        {
            "kanji": "辛い",
            "kana": "からい",
            "en": "spicy, hot"
        },
        {
            "kanji": "塩辛い",
            "kana": "しおからい",
            "en": "salty"
        },
        {
            "kanji": "酸っぱい",
            "kana": "すっぱい",
            "en": "sour"
        },
        {
            "kanji": "苦い",
            "kana": "にがい",
            "en": "bitter"
        }
    ]
}
